milvus_ingest-0.1.2.dist-info/METADATA
milvus_ingest-0.1.2.dist-info/WHEEL
milvus_ingest-0.1.2.dist-info/entry_points.txt
milvus_ingest/__init__.py
milvus_ingest/builtin_schemas.py
milvus_ingest/cli.py
milvus_ingest/exceptions.py
milvus_ingest/generator.py
milvus_ingest/logging_config.py
milvus_ingest/milvus_importer.py
milvus_ingest/milvus_inserter.py
milvus_ingest/milvus_schema_builder.py
milvus_ingest/models.py
milvus_ingest/optimized_writer.py
milvus_ingest/rich_display.py
milvus_ingest/schema_manager.py
milvus_ingest/schemas/__init__.py
milvus_ingest/schemas/ai_conversations.json
milvus_ingest/schemas/audio_transcripts.json
milvus_ingest/schemas/bm25_demo.json
milvus_ingest/schemas/cardinality_demo.json
milvus_ingest/schemas/default_values_demo.json
milvus_ingest/schemas/documents.json
milvus_ingest/schemas/dynamic_example.json
milvus_ingest/schemas/ecommerce.json
milvus_ingest/schemas/ecommerce_partitioned.json
milvus_ingest/schemas/face_recognition.json
milvus_ingest/schemas/force_modes_demo.json
milvus_ingest/schemas/full_text_search.json
milvus_ingest/schemas/images.json
milvus_ingest/schemas/news.json
milvus_ingest/schemas/simple.json
milvus_ingest/schemas/users.json
milvus_ingest/schemas/videos.json
milvus_ingest/uploader.py
milvus_ingest-0.1.2.dist-info/RECORD
