Metadata-Version: 2.1
Name: milvus-ingest
Version: 0.1.2
Summary: High-performance data ingestion tool for Milvus vector database with vectorized operations
Keywords: milvus,vector-database,data-ingestion,bulk-import,data-generation,high-performance,vectorization,etl
Author-Email: zhuwenxing <wenxing.zhu@zilliz.com>
License: MIT
Classifier: Development Status :: 4 - Beta
Classifier: Intended Audience :: Developers
Classifier: License :: OSI Approved :: MIT License
Classifier: Programming Language :: Python :: 3
Classifier: Programming Language :: Python :: 3.10
Classifier: Programming Language :: Python :: 3.11
Classifier: Programming Language :: Python :: 3.12
Classifier: Topic :: Database
Classifier: Topic :: Software Development :: Testing
Classifier: Topic :: Scientific/Engineering
Classifier: Topic :: System :: Benchmark
Classifier: Operating System :: OS Independent
Requires-Python: >=3.10
Requires-Dist: faker>=23.0.0
Requires-Dist: numpy>=1.24.0
Requires-Dist: pandas>=2.0.0
Requires-Dist: pyarrow>=14.0.0
Requires-Dist: click>=8.0.0
Requires-Dist: pyyaml>=6.0.0
Requires-Dist: pymilvus[bulk_writer]
Requires-Dist: pydantic>=2.0.0
Requires-Dist: rich>=13.0.0
Requires-Dist: loguru>=0.7.3
Requires-Dist: boto3>=1.28.0
Requires-Dist: ml-dtypes>=0.5.1
Provides-Extra: dev
Requires-Dist: pytest>=7.0.0; extra == "dev"
Requires-Dist: pytest-cov>=4.0.0; extra == "dev"
Requires-Dist: ruff>=0.1.0; extra == "dev"
Requires-Dist: mypy>=1.0.0; extra == "dev"
Requires-Dist: twine>=6.1.0; extra == "dev"
